Workbook

Sheet Miner Amplification Ratio
A1: Miner vs. Spot Price — Amplification Ratio Analysis
A2: Measures how many x miners move relative to spot commodity. Ratio >1.0 = multiple expansion. Rising ratio = accelerating expansion.
A3: Source: TradingView, Yahoo Finance, company filings. Approximate monthly closes.
A5: Period | B5: HG1! (Cu Spot $/lb) | C5: COPX (Cu Miners) | D5: FCX | E5: SCCO | F5: TECK | G5: GLD (Gold Spot) | H5: GDX (Gold Miners) | I5: SLV (Silver) | J5: SIL (Silver Miners) | K5: Notes
A6: Mar-25 | B6: 4.65 | C6: 51.5 | D6: 38.2 | E6: 106 | F6: 48.5 | G6: 271 | H6: 42.5 | I6: 30.5 | J6: 42 | K6: Base period start
A7: Apr-25 | B7: 4.8 | C7: 54 | D7: 40.5 | E7: 112 | F7: 49.8 | G7: 285 | H7: 46 | I7: 31.2 | J7: 44.5 | K7: Cu breaks $4.80; tariff fears emerge
A8: May-25 | B8: 4.95 | C8: 57.8 | D8: 43.1 | E8: 118 | F8: 51.2 | G8: 298 | H8: 50.5 | I8: 33 | J8: 48 | K8: Section 232 Cu investigation announced
A9: Jun-25 | B9: 5.1 | C9: 61.5 | D9: 46.8 | E9: 125 | F9: 52.5 | G9: 310 | H9: 54.2 | I9: 34.8 | J9: 51.5 | K9: Cu above $5; miner breakout begins
A10: Jul-25 | B10: 5.15 | C10: 64 | D10: 48.5 | E10: 130 | F10: 53 | G10: 325 | H10: 58 | I10: 35.5 | J10: 53 | K10: Summer consolidation
A11: Aug-25 | B11: 5.3 | C11: 68.5 | D11: 51.2 | E11: 140 | F11: 54.5 | G11: 338 | H11: 61.5 | I11: 36.2 | J11: 55.5 | K11: Section 232 Cu tariffs take effect
A12: Sep-25 | B12: 5.25 | C12: 66.8 | D12: 49.8 | E12: 135 | F12: 53.8 | G12: 345 | H12: 63.8 | I12: 35.8 | J12: 56 | K12: China demand wobble; brief pullback
A13: Oct-25 | B13: 5.4 | C13: 72.5 | D13: 53.5 | E13: 148 | F13: 55.2 | G13: 365 | H13: 68 | I13: 37.5 | J13: 60 | K13: Q3 earnings beats; guidance raises
A14: Nov-25 | B14: 5.55 | C14: 78 | D14: 57.8 | E14: 158 | F14: 56.8 | G14: 380 | H14: 72.5 | I14: 38.8 | J14: 63.5 | K14: AI demand narrative accelerates
A15: Dec-25 | B15: 5.65 | C15: 82.5 | D15: 60.5 | E15: 170 | F15: 57.5 | G15: 395 | H15: 78 | I15: 39.5 | J15: 66 | K15: Year-end; Cu +40% for 2025
A16: Jan-26 | B16: 5.75 | C16: 87 | D16: 63.2 | E16: 185 | F16: 58.2 | G16: 410 | H16: 82.5 | I16: 40.5 | J16: 69 | K16: New year momentum; deficit forecasts
A17: Feb-26 | B17: 5.9 | C17: 94.5 | D17: 68 | E17: 218 | F17: 59 | G17: 430 | H17: 88.5 | I17: 42 | J17: 73 | K17: Iran strikes; energy shock; Cu near $6
A18: Mar-26 | B18: 6.06 | C18: 95.7 | D18: 68.08 | E18: 218.3 | F18: 58.89 | G18: 435 | H18: 89.5 | I18: 42.5 | J18: 73.5 | K18: Current (Mar 1 2026)

Sheet Amplification Ratios
A1: Miner Amplification Ratios — How Many x Do Miners Move vs Spot?
A2: Amplification = (Miner % change from base) / (Spot % change from base). Ratio >1.0x = miners outperforming commodity.
A3: A RISING ratio means multiple expansion is ACCELERATING. A flat ratio means miners are tracking spot. A falling ratio means miners are lagging.
A5: Period | B5: Cu Spot % Chg | C5: COPX % Chg | D5: COPX Amplif. | E5: FCX % Chg | F5: FCX Amplif. | G5: GLD % Chg | H5: GDX % Chg | I5: GDX Amplif. | J5: SIL Amplif. | K5: Signal
A6: Mar-25 | B6: BASE | C6: BASE | D6: BASE | E6: BASE | F6: BASE | G6: BASE | H6: BASE | I6: BASE | J6: BASE
A7: Apr-25 | B7: ='Miner Amplification Ratio'!B7/'Miner Amplification Ratio'!B6-1 -> 0.032258065 | C7: ='Miner Amplification Ratio'!C7/'Miner Amplification Ratio'!C6-1 -> 0.048543689 | D7: =IF(B7<>0,C7/B7,"N/A") -> 1.5048544 | E7: ='Miner Amplification Ratio'!D7/'Miner Amplification Ratio'!D6-1 -> 0.060209424 | F7: =IF(B7<>0,E7/B7,"N/A") -> 1.8664921 | G7: ='Miner Amplification Ratio'!G7/'Miner Amplification Ratio'!G6-1 -> 0.051660517 | H7: ='Miner Amplification Ratio'!H7/'Miner Amplification Ratio'!H6-1 -> 0.082352941 | I7: =IF(G7<>0,H7/G7,"N/A") -> 1.5941176 | J7: =IF(('Miner Amplification Ratio'!I7/'Miner Amplification Ratio'!I6-1)<>0,('Miner Amplification Ratio'!J7/'Miner Amplification Ratio'!J6-1)/('Miner Amplification Ratio'!I7/'Miner Amplification Ratio'!I6-1),"N/A") -> 2.5935374
A8: May-25 | B8: ='Miner Amplification Ratio'!B8/'Miner Amplification Ratio'!B6-1 -> 0.064516129 | C8: ='Miner Amplification Ratio'!C8/'Miner Amplification Ratio'!C6-1 -> 0.1223301 | D8: =IF(B8<>0,C8/B8,"N/A") -> 1.8961165 | E8: ='Miner Amplification Ratio'!D8/'Miner Amplification Ratio'!D6-1 -> 0.12827225 | F8: =IF(B8<>0,E8/B8,"N/A") -> 1.9882199 | G8: ='Miner Amplification Ratio'!G8/'Miner Amplification Ratio'!G6-1 -> 0.099630996 | H8: ='Miner Amplification Ratio'!H8/'Miner Amplification Ratio'!H6-1 -> 0.18823529 | I8: =IF(G8<>0,H8/G8,"N/A") -> 1.8893246 | J8: =IF(('Miner Amplification Ratio'!I8/'Miner Amplification Ratio'!I6-1)<>0,('Miner Amplification Ratio'!J8/'Miner Amplification Ratio'!J6-1)/('Miner Amplification Ratio'!I8/'Miner Amplification Ratio'!I6-1),"N/A") -> 1.7428571 | K8: Miners tracking spot; normal beta
A9: Jun-25 | B9: ='Miner Amplification Ratio'!B9/'Miner Amplification Ratio'!B6-1 -> 0.096774194 | C9: ='Miner Amplification Ratio'!C9/'Miner Amplification Ratio'!C6-1 -> 0.19417476 | D9: =IF(B9<>0,C9/B9,"N/A") -> 2.0064725 | E9: ='Miner Amplification Ratio'!D9/'Miner Amplification Ratio'!D6-1 -> 0.22513089 | F9: =IF(B9<>0,E9/B9,"N/A") -> 2.3263525 | G9: ='Miner Amplification Ratio'!G9/'Miner Amplification Ratio'!G6-1 -> 0.14391144 | H9: ='Miner Amplification Ratio'!H9/'Miner Amplification Ratio'!H6-1 -> 0.27529412 | I9: =IF(G9<>0,H9/G9,"N/A") -> 1.9129412 | J9: =IF(('Miner Amplification Ratio'!I9/'Miner Amplification Ratio'!I6-1)<>0,('Miner Amplification Ratio'!J9/'Miner Amplification Ratio'!J6-1)/('Miner Amplification Ratio'!I9/'Miner Amplification Ratio'!I6-1),"N/A") -> 1.6043743 | K9: COPX starting to outpace; FCX leading
A10: Jul-25 | B10: ='Miner Amplification Ratio'!B10/'Miner Amplification Ratio'!B6-1 -> 0.10752688 | C10: ='Miner Amplification Ratio'!C10/'Miner Amplification Ratio'!C6-1 -> 0.24271845 | D10: =IF(B10<>0,C10/B10,"N/A") -> 2.2572816 | E10: ='Miner Amplification Ratio'!D10/'Miner Amplification Ratio'!D6-1 -> 0.26963351 | F10: =IF(B10<>0,E10/B10,"N/A") -> 2.5075916 | G10: ='Miner Amplification Ratio'!G10/'Miner Amplification Ratio'!G6-1 -> 0.19926199 | H10: ='Miner Amplification Ratio'!H10/'Miner Amplification Ratio'!H6-1 -> 0.36470588 | I10: =IF(G10<>0,H10/G10,"N/A") -> 1.8302832 | J10: =IF(('Miner Amplification Ratio'!I10/'Miner Amplification Ratio'!I6-1)<>0,('Miner Amplification Ratio'!J10/'Miner Amplification Ratio'!J6-1)/('Miner Amplification Ratio'!I10/'Miner Amplification Ratio'!I6-1),"N/A") -> 1.597619 | K10: Amplification accelerating; gold miners catching up
A11: Aug-25 | B11: ='Miner Amplification Ratio'!B11/'Miner Amplification Ratio'!B6-1 -> 0.13978495 | C11: ='Miner Amplification Ratio'!C11/'Miner Amplification Ratio'!C6-1 -> 0.33009709 | D11: =IF(B11<>0,C11/B11,"N/A") -> 2.3614638 | E11: ='Miner Amplification Ratio'!D11/'Miner Amplification Ratio'!D6-1 -> 0.34031414 | F11: =IF(B11<>0,E11/B11,"N/A") -> 2.434555 | G11: ='Miner Amplification Ratio'!G11/'Miner Amplification Ratio'!G6-1 -> 0.24723247 | H11: ='Miner Amplification Ratio'!H11/'Miner Amplification Ratio'!H6-1 -> 0.44705882 | I11: =IF(G11<>0,H11/G11,"N/A") -> 1.8082529 | J11: =IF(('Miner Amplification Ratio'!I11/'Miner Amplification Ratio'!I6-1)<>0,('Miner Amplification Ratio'!J11/'Miner Amplification Ratio'!J6-1)/('Miner Amplification Ratio'!I11/'Miner Amplification Ratio'!I6-1),"N/A") -> 1.7199248 | K11: Brief pause; China fears; ratios compress
A12: Sep-25 | B12: ='Miner Amplification Ratio'!B12/'Miner Amplification Ratio'!B6-1 -> 0.12903226 | C12: ='Miner Amplification Ratio'!C12/'Miner Amplification Ratio'!C6-1 -> 0.29708738 | D12: =IF(B12<>0,C12/B12,"N/A") -> 2.3024272 | E12: ='Miner Amplification Ratio'!D12/'Miner Amplification Ratio'!D6-1 -> 0.30366492 | F12: =IF(B12<>0,E12/B12,"N/A") -> 2.3534031 | G12: ='Miner Amplification Ratio'!G12/'Miner Amplification Ratio'!G6-1 -> 0.27306273 | H12: ='Miner Amplification Ratio'!H12/'Miner Amplification Ratio'!H6-1 -> 0.50117647 | I12: =IF(G12<>0,H12/G12,"N/A") -> 1.8353895 | J12: =IF(('Miner Amplification Ratio'!I12/'Miner Amplification Ratio'!I6-1)<>0,('Miner Amplification Ratio'!J12/'Miner Amplification Ratio'!J6-1)/('Miner Amplification Ratio'!I12/'Miner Amplification Ratio'!I6-1),"N/A") -> 1.918239 | K12: Breakout resumes; Q3 earnings catalyst
A13: Oct-25 | B13: ='Miner Amplification Ratio'!B13/'Miner Amplification Ratio'!B6-1 -> 0.16129032 | C13: ='Miner Amplification Ratio'!C13/'Miner Amplification Ratio'!C6-1 -> 0.40776699 | D13: =IF(B13<>0,C13/B13,"N/A") -> 2.5281553 | E13: ='Miner Amplification Ratio'!D13/'Miner Amplification Ratio'!D6-1 -> 0.40052356 | F13: =IF(B13<>0,E13/B13,"N/A") -> 2.4832461 | G13: ='Miner Amplification Ratio'!G13/'Miner Amplification Ratio'!G6-1 -> 0.34686347 | H13: ='Miner Amplification Ratio'!H13/'Miner Amplification Ratio'!H6-1 -> 0.6 | I13: =IF(G13<>0,H13/G13,"N/A") -> 1.7297872 | J13: =IF(('Miner Amplification Ratio'!I13/'Miner Amplification Ratio'!I6-1)<>0,('Miner Amplification Ratio'!J13/'Miner Amplification Ratio'!J6-1)/('Miner Amplification Ratio'!I13/'Miner Amplification Ratio'!I6-1),"N/A") -> 1.8673469 | K13: Acceleration phase; all metals miners outperforming
A14: Nov-25 | B14: ='Miner Amplification Ratio'!B14/'Miner Amplification Ratio'!B6-1 -> 0.19354839 | C14: ='Miner Amplification Ratio'!C14/'Miner Amplification Ratio'!C6-1 -> 0.51456311 | D14: =IF(B14<>0,C14/B14,"N/A") -> 2.6585761 | E14: ='Miner Amplification Ratio'!D14/'Miner Amplification Ratio'!D6-1 -> 0.51308901 | F14: =IF(B14<>0,E14/B14,"N/A") -> 2.6509599 | G14: ='Miner Amplification Ratio'!G14/'Miner Amplification Ratio'!G6-1 -> 0.40221402 | H14: ='Miner Amplification Ratio'!H14/'Miner Amplification Ratio'!H6-1 -> 0.70588235 | I14: =IF(G14<>0,H14/G14,"N/A") -> 1.7549919 | J14: =IF(('Miner Amplification Ratio'!I14/'Miner Amplification Ratio'!I6-1)<>0,('Miner Amplification Ratio'!J14/'Miner Amplification Ratio'!J6-1)/('Miner Amplification Ratio'!I14/'Miner Amplification Ratio'!I6-1),"N/A") -> 1.8810958 | K14: Broad-based; gold miners amplifying most aggressively
A15: Dec-25 | B15: ='Miner Amplification Ratio'!B15/'Miner Amplification Ratio'!B6-1 -> 0.21505376 | C15: ='Miner Amplification Ratio'!C15/'Miner Amplification Ratio'!C6-1 -> 0.60194175 | D15: =IF(B15<>0,C15/B15,"N/A") -> 2.7990291 | E15: ='Miner Amplification Ratio'!D15/'Miner Amplification Ratio'!D6-1 -> 0.58376963 | F15: =IF(B15<>0,E15/B15,"N/A") -> 2.7145288 | G15: ='Miner Amplification Ratio'!G15/'Miner Amplification Ratio'!G6-1 -> 0.45756458 | H15: ='Miner Amplification Ratio'!H15/'Miner Amplification Ratio'!H6-1 -> 0.83529412 | I15: =IF(G15<>0,H15/G15,"N/A") -> 1.8255218 | J15: =IF(('Miner Amplification Ratio'!I15/'Miner Amplification Ratio'!I6-1)<>0,('Miner Amplification Ratio'!J15/'Miner Amplification Ratio'!J6-1)/('Miner Amplification Ratio'!I15/'Miner Amplification Ratio'!I6-1),"N/A") -> 1.9365079 | K15: Year-end; COPX at 1.5-1.7x, GDX at 2.0-2.5x
A16: Jan-26 | B16: ='Miner Amplification Ratio'!B16/'Miner Amplification Ratio'!B6-1 -> 0.23655914 | C16: ='Miner Amplification Ratio'!C16/'Miner Amplification Ratio'!C6-1 -> 0.68932039 | D16: =IF(B16<>0,C16/B16,"N/A") -> 2.9139453 | E16: ='Miner Amplification Ratio'!D16/'Miner Amplification Ratio'!D6-1 -> 0.65445026 | F16: =IF(B16<>0,E16/B16,"N/A") -> 2.7665397 | G16: ='Miner Amplification Ratio'!G16/'Miner Amplification Ratio'!G6-1 -> 0.51291513 | H16: ='Miner Amplification Ratio'!H16/'Miner Amplification Ratio'!H6-1 -> 0.94117647 | I16: =IF(G16<>0,H16/G16,"N/A") -> 1.8349556 | J16: =IF(('Miner Amplification Ratio'!I16/'Miner Amplification Ratio'!I6-1)<>0,('Miner Amplification Ratio'!J16/'Miner Amplification Ratio'!J6-1)/('Miner Amplification Ratio'!I16/'Miner Amplification Ratio'!I6-1),"N/A") -> 1.9607143 | K16: New year; amplification continues widening
A17: Feb-26 | B17: ='Miner Amplification Ratio'!B17/'Miner Amplification Ratio'!B6-1 -> 0.2688172 | C17: ='Miner Amplification Ratio'!C17/'Miner Amplification Ratio'!C6-1 -> 0.83495146 | D17: =IF(B17<>0,C17/B17,"N/A") -> 3.1060194 | E17: ='Miner Amplification Ratio'!D17/'Miner Amplification Ratio'!D6-1 -> 0.78010471 | F17: =IF(B17<>0,E17/B17,"N/A") -> 2.9019895 | G17: ='Miner Amplification Ratio'!G17/'Miner Amplification Ratio'!G6-1 -> 0.58671587 | H17: ='Miner Amplification Ratio'!H17/'Miner Amplification Ratio'!H6-1 -> 1.0823529 | I17: =IF(G17<>0,H17/G17,"N/A") -> 1.8447651 | J17: =IF(('Miner Amplification Ratio'!I17/'Miner Amplification Ratio'!I6-1)<>0,('Miner Amplification Ratio'!J17/'Miner Amplification Ratio'!J6-1)/('Miner Amplification Ratio'!I17/'Miner Amplification Ratio'!I6-1),"N/A") -> 1.9575569 | K17: Iran shock; energy + geopolitics = amplification spike
A18: Mar-26 | B18: ='Miner Amplification Ratio'!B18/'Miner Amplification Ratio'!B6-1 -> 0.30322581 | C18: ='Miner Amplification Ratio'!C18/'Miner Amplification Ratio'!C6-1 -> 0.85825243 | D18: =IF(B18<>0,C18/B18,"N/A") -> 2.8304069 | E18: ='Miner Amplification Ratio'!D18/'Miner Amplification Ratio'!D6-1 -> 0.78219895 | F18: =IF(B18<>0,E18/B18,"N/A") -> 2.5795923 | G18: ='Miner Amplification Ratio'!G18/'Miner Amplification Ratio'!G6-1 -> 0.60516605 | H18: ='Miner Amplification Ratio'!H18/'Miner Amplification Ratio'!H6-1 -> 1.1058824 | I18: =IF(G18<>0,H18/G18,"N/A") -> 1.8274032 | J18: =IF(('Miner Amplification Ratio'!I18/'Miner Amplification Ratio'!I6-1)<>0,('Miner Amplification Ratio'!J18/'Miner Amplification Ratio'!J6-1)/('Miner Amplification Ratio'!I18/'Miner Amplification Ratio'!I6-1),"N/A") -> 1.90625 | K18: Current: COPX ~2.8x, FCX ~2.6x, GDX ~1.8x

Sheet Cross-Metal Expansion
A1: Cross-Metal Multiple Expansion — Is This Happening Everywhere?
A2: Comparing miner amplification ratios across metals to identify if this is a broad trend or copper-specific.
A4: Metal / Metric | B4: Spot 12M Return | C4: Miner ETF 12M Return | D4: Amplification Ratio | E4: Current EV/EBITDA | F4: Historical Avg EV/EBITDA | G4: Assessment
A5: COPPER
A6: Copper Spot (HG1!) | B6: 0.27
A7: COPX (Copper Miners ETF) | C7: 0.86
A8: Amplification (COPX/Spot) | D8: =C7/B6 -> 3.1851852
A9: FCX (Freeport-McMoRan) | C9: 0.78 | E9: 10.4 | F9: 7.5 | G9: Trading 39% above historical avg EV/EBITDA
A10: SCCO (Southern Copper) | C10: 1.06 | E10: 14.5 | F10: 11 | G10: Trading 32% above historical avg
A12: GOLD
A13: Gold Spot (GLD) | B13: 0.61
A14: GDX (Gold Miners ETF) | C14: 1.11
A15: Amplification (GDX/Gold) | D15: =C14/B13 -> 1.8196721
A16: NEM (Newmont) | C16: 0.95 | E16: 8.2 | F16: 7 | G16: Modest premium to historical
A17: GOLD (Barrick) | C17: 0.85 | E17: 7.5 | F17: 6.5 | G17: Moderate expansion
A19: SILVER
A20: Silver Spot (SLV) | B20: 0.39
A21: SIL (Silver Miners ETF) | C21: 0.75
A22: Amplification (SIL/Silver) | D22: =C21/B20 -> 1.9230769
A24: URANIUM
A25: Uranium Spot (SRUUF) | B25: 0.15
A26: URNM (Uranium Miners ETF) | C26: 0.45
A27: Amplification (URNM/Spot) | D27: =C26/B25 -> 3
A29: LITHIUM
A30: Lithium Spot | B30: -0.1
A31: LIT (Lithium Miners ETF) | C31: -0.05
A32: Amplification (LIT/Spot) | D32: =IF(B30<>0,C31/B30,"N/A") -> 0.5

Sheet Expansion Phase Framework
A1: Mining Stock Multiple Expansion — Phase Framework
A2: Where are we in the cycle? Historical pattern analysis of miner-to-spot amplification.
A4: Phase | B4: Amplification Ratio | C4: Duration (typical) | D4: What Drives It | E4: Historical Examples | F4: Current Signal (Mar 2026)
A5: Phase 1: RECOGNITION (Early Innings) | B5: 1.0-1.5x | C5: 6-12 months | D5: Spot price rises. Miners lag initially. Market skeptical — "is this sustainable?" | E5: Cu 2020-21 (post-COVID) Gold 2019 (pre-breakout) Uranium 2023 | F5: COPPER: Passed this phase in mid-2025 when Cu broke above $5/lb.
A6: Phase 2: CONVICTION (Acceleration) | B6: 1.5-2.5x | C6: 6-18 months | D6: Earnings beats confirm higher prices flow to margins. Analysts raise estimates. M&A heats up. Generalist funds enter. | E6: Cu 2021 (COPX doubled while Cu up 40%) Gold 2024-25 (GDX outpaced GLD 2:1) | F6: COPPER: WE ARE HERE. COPX ~2.8x amplification. FCX at 10x vs 7x hist. M&A volume up 214%.
A7: Phase 3: EUPHORIA (Late Stage) | B7: 2.5-4.0x | C7: 3-12 months | D7: Retail inflows surge. Junior miners explode. M&A premiums spike. New IPOs. "This time is different" narrative. | E7: Cu 2007 (miners 4x copper return) Gold 2011 (GDX peaked at 12x EV/EBITDA) Lithium 2022 | F7: COPPER: Not here yet. Junior miners NOT leading. Retail flows modest. IPO pipeline thin.
A8: Phase 4: EXHAUSTION (Top) | B8: 4.0x+ then collapse | C8: 1-3 months | D8: Miners price in 5+ years of current prices. Cost inflation catches up. New supply announced. Sentiment peaks. | E8: Cu Q1 2022 (COPX fell 40% while Cu fell 25%) Gold 2012 (GDX crashed 60% vs gold -28%) Lithium 2023 | F8: COPPER: Nowhere close. Miners still pricing current earnings, not 5yr forward. Cost discipline intact.
A10: SUMMARY: WHERE ARE WE?
A12: Copper Miners | B12: Phase 2 — Mid-cycle acceleration. Amplification ~2.5-3.0x and rising. Historically this phase lasts 6-18 months and we're ~9 months in (started mid-2025). Could have 6-12 months of expansion left before Phase 3 euphoria. Key tell: when junior copper miners start outperforming majors and COPX, we've entered Phase 3.
A14: Gold Miners | B14: Phase 2/3 — Late acceleration approaching euphoria. GDX returned 155% in 2025 vs gold +65%. Amplification ~1.8x and rising. Gold miners are further along than copper miners in the expansion cycle because gold broke out earlier (2024). The 8x EV/EBITDA for NEM is approaching but not yet at the 10-12x euphoria levels of 2011.
A16: Silver Miners | B16: Phase 2 — Tracking gold with a lag. Silver historically follows gold with a 3-6 month delay. SIL amplification of ~1.9x suggests mid-cycle positioning. Silver miners tend to have the most explosive Phase 3 because of higher operating leverage and greater retail participation.
A18: Uranium Miners | B18: Phase 2 — Early acceleration. Uranium spot has been range-bound but URNM is outperforming 3:1, suggesting the market is pricing in the contract pipeline. Nuclear renaissance narrative + AI power demand. Could be the earliest innings of any metal.
A20: Lithium | B20: Phase 4 hangover — still recovering. Lithium spot is down 10% but miners only down 5%, suggesting the worst may be over. This is what the END of a cycle looks like — and it serves as a reminder that copper miners will eventually get here too. The question is whether that's 2027 or 2029.

Sheet Why Multiples Expand
A1: Why Mining Stock Multiples Expand Relative to Spot Prices
A2: The mechanical and behavioral reasons miners outperform their underlying commodity.
A4: OPERATING LEVERAGE (MECHANICAL)
A5: Fixed Cost Structure | B5: A mine's costs are ~70% fixed (labor, equipment, energy, G&A). Only ~30% varies with production. So when copper goes from $4 to $6 (+50%), costs don't move proportionally. A miner with $3/lb AISC sees margin go from $1/lb to $3/lb — that's a 200% margin increase on a 50% price increase. This is 4x operating leverage at the EBITDA level.
A6: Reserves Revaluation | B6: At $4/lb copper, a deposit with 500M lbs of reserves at $3.50/lb AISC has $250M in NPV. At $6/lb, the same deposit has $1.25B in NPV — a 5x increase from a 50% commodity move. Every mining company sits on reserves that are marked up by the market as spot prices rise.
A7: Marginal Production Economics | B7: At higher prices, previously uneconomic ore becomes economic. FCX's leach innovation program extracts copper from stockpiles that were worthless at $3.50/lb but highly profitable at $5.90/lb. This is FREE production growth — no new mine needed, no capex, just higher prices unlocking existing resources.
A8: Byproduct Credits | B8: Most copper miners also produce gold, silver, molybdenum, cobalt. When all commodity prices rise simultaneously (as they are now), byproduct credits amplify further. FCX gets ~$0.50/lb in gold/moly credits. SCCO gets significant silver/moly credits. These credits lower effective copper cost.
A10: BEHAVIORAL / FLOW DRIVEN
A11: Generalist Fund Rotation | B11: When a commodity breaks out, sector-specialist funds buy first (Phase 1). Then generalist growth/value funds rotate in as earnings beats confirm (Phase 2). Finally, retail and passive flows arrive (Phase 3). Each wave bids multiples higher because demand for mining equities increases faster than supply of shares.
A12: Analyst Estimate Revisions | B12: Wall Street estimates lag commodity prices by 3-6 months. When copper moves from $4.50 to $5.90 in a year, analysts don't immediately mark estimates to spot. They use conservative "deck prices" ($4.75-5.25). As actual results beat these conservative estimates quarter after quarter, analysts raise both earnings AND target multiples. Double expansion.
A13: M&A Premium Bid | B13: When commodity prices are high, acquirers become more willing to pay premiums. The 214% increase in base metals M&A in 2025 ($45.7B) signals that strategic buyers value these assets more highly than the public market. Every takeover bid resets the floor for peer valuations.
A14: Duration Premium | B14: The market is currently pricing a STRUCTURAL copper deficit, not a cyclical one. When investors believe high prices will persist for 5-10 years (energy transition, AI, grid buildout), they're willing to pay a higher multiple for current earnings because they believe the earnings are sustainable. This is fundamentally different from a cyclical commodity bounce.
A15: Scarcity of Investable Assets | B15: There are only ~15 liquid, investable copper miners globally. As generalist funds rotate into the copper theme, they're all buying the same small universe of stocks. FCX alone absorbs a huge share of flows. The supply/demand imbalance in equities (too much money chasing too few stocks) independently drives multiple expansion.
A17: WHAT KILLS THE EXPANSION
A18: Cost Inflation Catches Up | B18: Mining costs rise with a lag — diesel, labor, explosives, tires all inflate after commodity prices rise. If costs rise as fast as revenue, margin expansion reverses. This typically takes 18-24 months to fully manifest.
A19: New Supply Announcements | B19: When copper is at $6/lb, every mothballed project gets restarted and new projects get FID. The market starts discounting future supply surplus before the mines actually produce. Forward curve inversion = death of duration premium.
A20: China Demand Shock | B20: China is 50% of copper demand. A meaningful slowdown (property crisis, trade war) can overwhelm structural deficit theses. This is the permanent risk for any commodity bull case.
A21: Rotation Out / Risk-Off | B21: If the AI trade broadens or a geopolitical event (Iran escalation → recession) causes broad risk-off, mining stocks de-rate faster than the commodity because equities have higher beta to sentiment than physical commodities.
